redis_hj3415/__init__.py
redis_hj3415/schemas.py
redis_hj3415/utils.py
redis_hj3415/wrapper.py
redis_hj3415/common/__init__.py
redis_hj3415/common/connection.py
redis_hj3415-0.2.4.dist-info/WHEEL
redis_hj3415-0.2.4.dist-info/METADATA
redis_hj3415-0.2.4.dist-info/RECORD
