Metadata-Version: 2.4
Name: redis_hj3415
Version: 0.2.4
Summary: redis-hj3415 is the program using redis module.
Author-email: Hyungjin Kim <hj3415@gmail.com>
Classifier: License :: OSI Approved :: MIT License
Requires-Dist: redis>=6.2.0
Project-URL: Home, https://www.hyungjin.kr
